Metadata-Version: 1.1
Name: jupyter-echarts-pypkg
Version: 0.1.5
Summary: Echarts pypi packages for jupyter and python
Home-page: https://github.com/pyecharts/jupyter-echarts-pypkg
Author: C.W.
Author-email: wangc_2011@hotmail.com
License: MIT
Download-URL: https://github.com/pyecharts/jupyter-echarts-pypkg/archive/0.1.5.tar.gz
Keywords: python
Platform: UNKNOWN
Classifier: Topic :: Software Development :: Libraries
Classifier: Programming Language :: Python
Classifier: Intended Audience :: Developers
Classifier: Programming Language :: Python :: 2.6
Classifier: Programming Language :: Python :: 2.7
Classifier: Programming Language :: Python :: 3.3
Classifier: Programming Language :: Python :: 3.4
Classifier: Programming Language :: Python :: 3.5
Classifier: Programming Language :: Python :: 3.6
